{
  "slug": "tech_iot_basics",
  "title": "IoT (Internet of Things) の基礎",
  "majorCategory": "technology",
  "minorTopic": "IoTとシステム",
  "summary": "IoTとは、センサや制御装置などの『モノ』が直接インターネットにつながり、ネットワークを通じて様々な情報をやり取りする仕組み。単なるWeb配信やクラウドへの移行はIoTではない。",
  "body": "## IoTの必要条件\n\n1. **モノ側にセンサ/制御装置** が付いている\n2. 人の介在なく **自動で** データをやり取りする\n3. インターネット (またはそれに準ずるネットワーク) に **直接** 接続\n\n## 具体例\n\n- ✅ 薬の容器にセンサを埋め込み、服薬履歴を自動収集\n- ✅ 工場設備の稼働データを自動収集して予兆保全\n- ✅ ウェアラブル端末が心拍や歩数を計測\n\n## IoTではないもの\n\n- ❌ Web会議やオンライン授業 (人が操作する単なる通信)\n- ❌ 社内サーバをクラウドへ移設 (クラウドコンピューティング)\n- ❌ オンラインオークション (Webサービス)\n"
}
